{"images/1.jpeg":["images/1.jpeg"],"images/2.jpeg":["images/2.jpeg"],"images/3.jpeg":["images/3.jpeg"],"images/4.jpeg":["images/4.jpeg"],"images/5.jpeg":["images/5.jpeg"],"images/bg.jpeg":["images/bg.jpeg"],"images/car.png":["images/car.png"],"images/care.png":["images/care.png"],"images/food.png":["images/food.png"],"images/other.png":["images/other.png"],"images/phone.png":["images/phone.png"],"images/pp.jpg":["images/pp.jpg"],"images/ride.png":["images/ride.png"],"images/scan.png":["images/scan.png"],"images/send.png":["images/send.png"],"images/shop.png":["images/shop.png"],"images/teledok.jpeg":["images/teledok.jpeg"],"packages/cupertino_icons/assets/CupertinoIcons.ttf":["packages/cupertino_icons/assets/CupertinoIcons.ttf"]}